requests_iap2/__init__.py
requests_iap2/_version.py
requests_iap2/constants.py
requests_iap2/create_client_id_file.py
requests_iap2/get_credentials.py
requests_iap2/iapauth.py
requests_iap2-2.1.0.dist-info/LICENSE
requests_iap2-2.1.0.dist-info/METADATA
requests_iap2-2.1.0.dist-info/WHEEL
requests_iap2-2.1.0.dist-info/top_level.txt
requests_iap2-2.1.0.dist-info/RECORD
