Metadata-Version: 2.1
Name: requests-iap2
Version: 2.1.0
Home-page: https://github.com/climateengine/requests-iap2
Author: Bennett Kanuka
Author-email: bennett@climateengine.com
Classifier: Environment :: Console
Classifier: Operating System :: OS Independent
Classifier: Programming Language :: Python :: 3
License-File: LICENSE
Requires-Dist: requests
Requires-Dist: google-auth
Requires-Dist: google-auth-oauthlib
Provides-Extra: dev
Requires-Dist: build ; extra == 'dev'
Requires-Dist: more-itertools (==5.0.0) ; extra == 'dev'
Requires-Dist: pip-tools ; extra == 'dev'
Requires-Dist: pytest (<5.0.0) ; extra == 'dev'
Requires-Dist: pytest-cov ; extra == 'dev'
Requires-Dist: pytest-mock (<3.3) ; extra == 'dev'
Requires-Dist: setuptools (>=42) ; extra == 'dev'
Requires-Dist: setuptools-scm[toml] (>=5.0.2) ; extra == 'dev'
Requires-Dist: tox ; extra == 'dev'
Requires-Dist: twine ; extra == 'dev'
Requires-Dist: wheel ; extra == 'dev'
